wordexceltools/__init__.py
wordexceltools/common_tools.py
wordexceltools/excel_tools.py
wordexceltools/word_tools.py
wordexceltools-1.1.0.dist-info/LICENSE
wordexceltools-1.1.0.dist-info/METADATA
wordexceltools-1.1.0.dist-info/WHEEL
wordexceltools-1.1.0.dist-info/top_level.txt
wordexceltools-1.1.0.dist-info/RECORD
