Metadata-Version: 2.1
Name: wordexceltools
Version: 1.1.0
Summary: An efficient toolkit for handling Excel files and generating Word documents, leveraging the power of python-docx and openpyxl.
Home-page: https://github.com/ldspdvsun/wordexceltools
Author: MengYue Sun
Author-email: ldspdvsun@gmail.com
License: Apache
Classifier: License :: OSI Approved :: MIT License
Classifier: Programming Language :: Python
Classifier: Programming Language :: Python :: 3
Classifier: Programming Language :: Python :: 3.6
Classifier: Programming Language :: Python :: Implementation :: CPython
Classifier: Programming Language :: Python :: Implementation :: PyPy
Requires-Python: >=3.6.0
License-File: LICENSE
Requires-Dist: chardet==4.0.0
Requires-Dist: docx==0.2.4
Requires-Dist: openpyxl==3.1.5
Requires-Dist: python_docx==1.1.2
